pynbn/__init__.py
pynbn-1.0.1.dist-info/DESCRIPTION.rst
pynbn-1.0.1.dist-info/METADATA
pynbn-1.0.1.dist-info/RECORD
pynbn-1.0.1.dist-info/WHEEL
pynbn-1.0.1.dist-info/metadata.json
pynbn-1.0.1.dist-info/top_level.txt
